{"cameraMode":{"drawMode":0,"name":"Shaded","section":"Shading Mode"},"sceneLighting":false,"audioPlay":false,"sceneViewState":{"m_AlwaysRefresh":false,"showFog":true,"showSkybox":false,"showFlares":true,"showImageEffects":true,"showParticleSystems":true,"showVisualEffectGraphs":true,"m_FxEnabled":true},"in2DMode":false,"pivot":{"x":-1.714043140411377,"y":1.3120698928833008,"z":-31.06766700744629},"rotation":{"x":-0.13173140585422517,"y":0.6834259033203125,"z":-0.12821583449840547,"w":-0.7070102691650391},"size":1.462801456451416,"orthographic":false}